<?xml version="1.0" encoding="UTF-8"?>
<urdf_part>
    <material name="#EDEDED">
        <color rgba="0.933000 0.933000 0.933000 1.0" />
    </material>
    <link name="l_shoulder">
        <visual>
            <origin xyz="0.000000 0.000000 0.000000" rpy="0 0 0"/>
            <material name="#EDEDED" />
        </visual>
        <inertial>
            <origin xyz="0.000000 0.000000 0.000000"/>
            <mass value="0.014"/>
            <volume value="0.000019737495"/>
            <inertia ixx="0.00001591" ixy="-0.00000067" ixz="0.00000047" iyy="0.00002186" iyz="-0.00000033" izz="0.00002647"/>
        </inertial>
        <center_of_mass>0.000000 0.000000 0.000000</center_of_mass>
    </link>
    <point name="point1" type="fixed">
        <point_xyz>0.019760 0.025600 -0.000020</point_xyz>
    </point>
    <joint>
        <axis xyz="0 1 0" />
    </joint>
</urdf_part>